mchost24/__init__.py
mchost24/__main__.py
mchost24/api.py
mchost24-1.0.1.dist-info/licenses/LICENSE
mchost24-1.0.1.dist-info/METADATA
mchost24-1.0.1.dist-info/WHEEL
mchost24-1.0.1.dist-info/top_level.txt
mchost24-1.0.1.dist-info/RECORD
