Metadata-Version: 2.4
Name: mchost24
Version: 1.0.1
Summary: A Python Module that allows interacting with the MC-Host24 REST API
Author-email: JoeJoeTV <joejoetv@joejoetv.de>
License-Expression: GPL-3.0
Project-URL: Homepage, https://github.com/JoeJoeTV/mchost24-api-python
Project-URL: Issues, https://github.com/JoeJoeTV/mchost24-api-python/issues
Classifier: Development Status :: 5 - Production/Stable
Classifier: Environment :: Console
Classifier: Intended Audience :: Developers
Classifier: Intended Audience :: System Administrators
Classifier: Operating System :: OS Independent
Classifier: Programming Language :: Python
Classifier: Programming Language :: Python :: 3
Classifier: Topic :: Internet
Classifier: Topic :: Internet :: WWW/HTTP
Classifier: Topic :: System :: Networking
Classifier: Topic :: Utilities
Requires-Python: >=3.10
License-File: LICENSE
Requires-Dist: dataclasses_json>=0.6.6
Requires-Dist: pytimeparse2>=1.7.1
Requires-Dist: requests>=2.32.3
Dynamic: license-file
